{
  "address": "57owAwKC7TkWzsHPdaL7XXWfbj8FS1YUUw4sxWWmBarm",
  "metadata": {
    "name": "sealed_auction_program",
    "version": "0.1.0",
    "spec": "0.1.0",
    "description": "Sealed-bid auction with MagicBlock ER + Private ER support"
  },
  "instructions": [
    {
      "name": "commit_bid",
      "discriminator": [
        149,
        237,
        198,
        113,
        53,
        66,
        70,
        76
      ],
      "accounts": [
        {
          "name": "bidder",
          "writable": true,
          "signer": true
        },
        {
          "name": "auction",
          "writable": true,
          "pda": {
            "seeds": [
              {
                "kind": "const",
                "value": [
                  97,
                  117,
                  99,
                  116,
                  105,
                  111,
                  110
                ]
              },
              {
                "kind": "arg",
                "path": "auction_id"
              }
            ]
          }
        },
        {
          "name": "bid",
          "writable": true,
          "pda": {
            "seeds": [
              {
                "kind": "const",
                "value": [
                  98,
                  105,
                  100
                ]
              },
              {
                "kind": "arg",
                "path": "auction_id"
              },
              {
                "kind": "account",
                "path": "bidder"
              }
            ]
          }
        },
        {
          "name": "runtime",
          "writable": true,
          "pda": {
            "seeds": [
              {
                "kind": "const",
                "value": [
                  114,
                  117,
                  110,
                  116,
                  105,
                  109,
                  101
                ]
              },
              {
                "kind": "arg",
                "path": "auction_id"
              }
            ]
          }
        },
        {
          "name": "system_program",
          "address": "11111111111111111111111111111111"
        }
      ],
      "args": [
        {
          "name": "auction_id",
          "type": "u64"
        },
        {
          "name": "commitment",
          "type": {
            "array": [
              "u8",
              32
            ]
          }
        }
      ]
    },
    {
      "name": "commit_runtime",
      "discriminator": [
        191,
        122,
        5,
        4,
        210,
        66,
        82,
        31
      ],
      "accounts": [
        {
          "name": "payer",
          "writable": true,
          "signer": true
        },
        {
          "name": "runtime",
          "writable": true,
          "pda": {
            "seeds": [
              {
                "kind": "const",
                "value": [
                  114,
                  117,
                  110,
                  116,
                  105,
                  109,
                  101
                ]
              },
              {
                "kind": "arg",
                "path": "auction_id"
              }
            ]
          }
        },
        {
          "name": "magic_program",
          "address": "Magic11111111111111111111111111111111111111"
        },
        {
          "name": "magic_context",
          "writable": true,
          "address": "MagicContext1111111111111111111111111111111"
        }
      ],
      "args": [
        {
          "name": "auction_id",
          "type": "u64"
        }
      ]
    },
    {
      "name": "compute_winner_private",
      "discriminator": [
        139,
        58,
        228,
        143,
        75,
        136,
        46,
        127
      ],
      "accounts": [
        {
          "name": "payer",
          "writable": true,
          "signer": true
        },
        {
          "name": "auction",
          "writable": true,
          "pda": {
            "seeds": [
              {
                "kind": "const",
                "value": [
                  97,
                  117,
                  99,
                  116,
                  105,
                  111,
                  110
                ]
              },
              {
                "kind": "arg",
                "path": "auction_id"
              }
            ]
          }
        }
      ],
      "args": [
        {
          "name": "auction_id",
          "type": "u64"
        },
        {
          "name": "winner",
          "type": "pubkey"
        },
        {
          "name": "winning_price",
          "type": "u64"
        },
        {
          "name": "aggregate_digest",
          "type": {
            "array": [
              "u8",
              32
            ]
          }
        }
      ]
    },
    {
      "name": "delegate_runtime",
      "discriminator": [
        67,
        199,
        221,
        168,
        34,
        75,
        166,
        251
      ],
      "accounts": [
        {
          "name": "payer",
          "writable": true,
          "signer": true
        },
        {
          "name": "buffer_runtime",
          "writable": true,
          "pda": {
            "seeds": [
              {
                "kind": "const",
                "value": [
                  98,
                  117,
                  102,
                  102,
                  101,
                  114
                ]
              },
              {
                "kind": "account",
                "path": "runtime"
              }
            ],
            "program": {
              "kind": "const",
              "value": [
                61,
                45,
                77,
                13,
                166,
                171,
                168,
                165,
                95,
                20,
                188,
                179,
                85,
                32,
                243,
                132,
                148,
                113,
                167,
                235,
                127,
                241,
                255,
                225,
                60,
                210,
                18,
                86,
                153,
                95,
                139,
                26
              ]
            }
          }
        },
        {
          "name": "delegation_record_runtime",
          "writable": true,
          "pda": {
            "seeds": [
              {
                "kind": "const",
                "value": [
                  100,
                  101,
                  108,
                  101,
                  103,
                  97,
                  116,
                  105,
                  111,
                  110
                ]
              },
              {
                "kind": "account",
                "path": "runtime"
              }
            ],
            "program": {
              "kind": "account",
              "path": "delegation_program"
            }
          }
        },
        {
          "name": "delegation_metadata_runtime",
          "writable": true,
          "pda": {
            "seeds": [
              {
                "kind": "const",
                "value": [
                  100,
                  101,
                  108,
                  101,
                  103,
                  97,
                  116,
                  105,
                  111,
                  110,
                  45,
                  109,
                  101,
                  116,
                  97,
                  100,
                  97,
                  116,
                  97
                ]
              },
              {
                "kind": "account",
                "path": "runtime"
              }
            ],
            "program": {
              "kind": "account",
              "path": "delegation_program"
            }
          }
        },
        {
          "name": "runtime",
          "writable": true,
          "pda": {
            "seeds": [
              {
                "kind": "const",
                "value": [
                  114,
                  117,
                  110,
                  116,
                  105,
                  109,
                  101
                ]
              },
              {
                "kind": "arg",
                "path": "auction_id"
              }
            ]
          }
        },
        {
          "name": "owner_program",
          "address": "57owAwKC7TkWzsHPdaL7XXWfbj8FS1YUUw4sxWWmBarm"
        },
        {
          "name": "delegation_program",
          "address": "DELeGGvXpWV2fqJUhqcF5ZSYMS4JTLjteaAMARRSaeSh"
        },
        {
          "name": "system_program",
          "address": "11111111111111111111111111111111"
        }
      ],
      "args": [
        {
          "name": "auction_id",
          "type": "u64"
        }
      ]
    },
    {
      "name": "initialize_auction",
      "discriminator": [
        37,
        10,
        117,
        197,
        208,
        88,
        117,
        62
      ],
      "accounts": [
        {
          "name": "seller",
          "writable": true,
          "signer": true
        },
        {
          "name": "token_mint"
        },
        {
          "name": "auction",
          "writable": true,
          "pda": {
            "seeds": [
              {
                "kind": "const",
                "value": [
                  97,
                  117,
                  99,
                  116,
                  105,
                  111,
                  110
                ]
              },
              {
                "kind": "arg",
                "path": "auction_id"
              }
            ]
          }
        },
        {
          "name": "runtime",
          "writable": true,
          "pda": {
            "seeds": [
              {
                "kind": "const",
                "value": [
                  114,
                  117,
                  110,
                  116,
                  105,
                  109,
                  101
                ]
              },
              {
                "kind": "arg",
                "path": "auction_id"
              }
            ]
          }
        },
        {
          "name": "vault",
          "writable": true,
          "pda": {
            "seeds": [
              {
                "kind": "account",
                "path": "auction"
              },
              {
                "kind": "const",
                "value": [
                  6,
                  221,
                  246,
                  225,
                  215,
                  101,
                  161,
                  147,
                  217,
                  203,
                  225,
                  70,
                  206,
                  235,
                  121,
                  172,
                  28,
                  180,
                  133,
                  237,
                  95,
                  91,
                  55,
                  145,
                  58,
                  140,
                  245,
                  133,
                  126,
                  255,
                  0,
                  169
                ]
              },
              {
                "kind": "account",
                "path": "token_mint"
              }
            ],
            "program": {
              "kind": "const",
              "value": [
                140,
                151,
                37,
                143,
                78,
                36,
                137,
                241,
                187,
                61,
                16,
                41,
                20,
                142,
                13,
                131,
                11,
                90,
                19,
                153,
                218,
                255,
                16,
                132,
                4,
                142,
                123,
                216,
                219,
                233,
                248,
                89
              ]
            }
          }
        },
        {
          "name": "system_program",
          "address": "11111111111111111111111111111111"
        },
        {
          "name": "token_program",
          "address": "TokenkegQfeZyiNwAJbNbGKPFXCWuBvf9Ss623VQ5DA"
        },
        {
          "name": "associated_token_program",
          "address": "ATokenGPvbdGVxr1b2hvZbsiqW5xWH25efTNsLJA8knL"
        }
      ],
      "args": [
        {
          "name": "auction_id",
          "type": "u64"
        },
        {
          "name": "bidding_start",
          "type": "i64"
        },
        {
          "name": "commit_end",
          "type": "i64"
        },
        {
          "name": "reveal_end",
          "type": "i64"
        },
        {
          "name": "private_mode",
          "type": "bool"
        }
      ]
    },
    {
      "name": "process_undelegation",
      "discriminator": [
        196,
        28,
        41,
        206,
        48,
        37,
        51,
        167
      ],
      "accounts": [
        {
          "name": "base_account",
          "writable": true
        },
        {
          "name": "buffer"
        },
        {
          "name": "payer",
          "writable": true
        },
        {
          "name": "system_program"
        }
      ],
      "args": [
        {
          "name": "account_seeds",
          "type": {
            "vec": "bytes"
          }
        }
      ]
    },
    {
      "name": "reveal_bid",
      "discriminator": [
        48,
        73,
        28,
        255,
        202,
        126,
        236,
        196
      ],
      "accounts": [
        {
          "name": "bidder",
          "writable": true,
          "signer": true
        },
        {
          "name": "auction",
          "writable": true,
          "pda": {
            "seeds": [
              {
                "kind": "const",
                "value": [
                  97,
                  117,
                  99,
                  116,
                  105,
                  111,
                  110
                ]
              },
              {
                "kind": "arg",
                "path": "auction_id"
              }
            ]
          }
        },
        {
          "name": "bid",
          "writable": true,
          "pda": {
            "seeds": [
              {
                "kind": "const",
                "value": [
                  98,
                  105,
                  100
                ]
              },
              {
                "kind": "arg",
                "path": "auction_id"
              },
              {
                "kind": "account",
                "path": "bidder"
              }
            ]
          }
        },
        {
          "name": "runtime",
          "writable": true,
          "pda": {
            "seeds": [
              {
                "kind": "const",
                "value": [
                  114,
                  117,
                  110,
                  116,
                  105,
                  109,
                  101
                ]
              },
              {
                "kind": "arg",
                "path": "auction_id"
              }
            ]
          }
        },
        {
          "name": "bidder_token",
          "writable": true
        },
        {
          "name": "vault",
          "writable": true
        },
        {
          "name": "token_program",
          "address": "TokenkegQfeZyiNwAJbNbGKPFXCWuBvf9Ss623VQ5DA"
        }
      ],
      "args": [
        {
          "name": "auction_id",
          "type": "u64"
        },
        {
          "name": "bid_amount",
          "type": "u64"
        },
        {
          "name": "salt",
          "type": "bytes"
        }
      ]
    },
    {
      "name": "settle_auction",
      "discriminator": [
        246,
        196,
        183,
        98,
        222,
        139,
        46,
        133
      ],
      "accounts": [
        {
          "name": "authority",
          "writable": true,
          "signer": true
        },
        {
          "name": "auction",
          "writable": true,
          "pda": {
            "seeds": [
              {
                "kind": "const",
                "value": [
                  97,
                  117,
                  99,
                  116,
                  105,
                  111,
                  110
                ]
              },
              {
                "kind": "arg",
                "path": "auction_id"
              }
            ]
          }
        },
        {
          "name": "vault",
          "writable": true
        },
        {
          "name": "seller_token",
          "writable": true
        },
        {
          "name": "token_program",
          "address": "TokenkegQfeZyiNwAJbNbGKPFXCWuBvf9Ss623VQ5DA"
        }
      ],
      "args": [
        {
          "name": "auction_id",
          "type": "u64"
        }
      ]
    },
    {
      "name": "settle_private",
      "discriminator": [
        220,
        119,
        140,
        233,
        54,
        178,
        252,
        237
      ],
      "accounts": [
        {
          "name": "authority",
          "writable": true,
          "signer": true
        },
        {
          "name": "auction",
          "writable": true,
          "pda": {
            "seeds": [
              {
                "kind": "const",
                "value": [
                  97,
                  117,
                  99,
                  116,
                  105,
                  111,
                  110
                ]
              },
              {
                "kind": "arg",
                "path": "auction_id"
              }
            ]
          }
        },
        {
          "name": "vault",
          "writable": true
        },
        {
          "name": "seller_token",
          "writable": true
        },
        {
          "name": "token_program",
          "address": "TokenkegQfeZyiNwAJbNbGKPFXCWuBvf9Ss623VQ5DA"
        }
      ],
      "args": [
        {
          "name": "auction_id",
          "type": "u64"
        }
      ]
    },
    {
      "name": "start_reveal",
      "discriminator": [
        53,
        233,
        172,
        216,
        107,
        91,
        161,
        239
      ],
      "accounts": [
        {
          "name": "payer",
          "writable": true,
          "signer": true
        },
        {
          "name": "auction",
          "writable": true,
          "pda": {
            "seeds": [
              {
                "kind": "const",
                "value": [
                  97,
                  117,
                  99,
                  116,
                  105,
                  111,
                  110
                ]
              },
              {
                "kind": "arg",
                "path": "auction_id"
              }
            ]
          }
        }
      ],
      "args": [
        {
          "name": "auction_id",
          "type": "u64"
        }
      ]
    },
    {
      "name": "submit_encrypted_bid",
      "discriminator": [
        79,
        24,
        114,
        130,
        197,
        38,
        79,
        99
      ],
      "accounts": [
        {
          "name": "bidder",
          "writable": true,
          "signer": true
        },
        {
          "name": "auction",
          "writable": true,
          "pda": {
            "seeds": [
              {
                "kind": "const",
                "value": [
                  97,
                  117,
                  99,
                  116,
                  105,
                  111,
                  110
                ]
              },
              {
                "kind": "arg",
                "path": "auction_id"
              }
            ]
          }
        },
        {
          "name": "bid_cipher",
          "writable": true,
          "pda": {
            "seeds": [
              {
                "kind": "const",
                "value": [
                  98,
                  105,
                  100,
                  95,
                  99,
                  105,
                  112,
                  104,
                  101,
                  114
                ]
              },
              {
                "kind": "arg",
                "path": "auction_id"
              },
              {
                "kind": "account",
                "path": "bidder"
              }
            ]
          }
        },
        {
          "name": "system_program",
          "address": "11111111111111111111111111111111"
        }
      ],
      "args": [
        {
          "name": "auction_id",
          "type": "u64"
        },
        {
          "name": "ciphertext",
          "type": "bytes"
        }
      ]
    },
    {
      "name": "undelegate_runtime",
      "discriminator": [
        117,
        183,
        58,
        246,
        102,
        117,
        199,
        168
      ],
      "accounts": [
        {
          "name": "payer",
          "writable": true,
          "signer": true
        },
        {
          "name": "runtime",
          "writable": true,
          "pda": {
            "seeds": [
              {
                "kind": "const",
                "value": [
                  114,
                  117,
                  110,
                  116,
                  105,
                  109,
                  101
                ]
              },
              {
                "kind": "arg",
                "path": "auction_id"
              }
            ]
          }
        },
        {
          "name": "magic_program",
          "address": "Magic11111111111111111111111111111111111111"
        },
        {
          "name": "magic_context",
          "writable": true,
          "address": "MagicContext1111111111111111111111111111111"
        }
      ],
      "args": [
        {
          "name": "auction_id",
          "type": "u64"
        }
      ]
    }
  ],
  "accounts": [
    {
      "name": "AuctionConfig",
      "discriminator": [
        195,
        54,
        8,
        51,
        28,
        231,
        33,
        142
      ]
    },
    {
      "name": "AuctionRuntime",
      "discriminator": [
        73,
        190,
        81,
        217,
        68,
        143,
        16,
        68
      ]
    },
    {
      "name": "BidCiphertext",
      "discriminator": [
        31,
        72,
        220,
        67,
        56,
        104,
        63,
        112
      ]
    },
    {
      "name": "BidCommitment",
      "discriminator": [
        22,
        176,
        22,
        172,
        16,
        35,
        239,
        176
      ]
    }
  ],
  "events": [
    {
      "name": "AuctionInitialized",
      "discriminator": [
        18,
        7,
        64,
        239,
        134,
        184,
        173,
        108
      ]
    },
    {
      "name": "AuctionSettled",
      "discriminator": [
        61,
        151,
        131,
        170,
        95,
        203,
        219,
        147
      ]
    },
    {
      "name": "BidCommitted",
      "discriminator": [
        81,
        13,
        193,
        139,
        0,
        168,
        82,
        55
      ]
    },
    {
      "name": "BidRevealed",
      "discriminator": [
        227,
        144,
        125,
        229,
        28,
        109,
        18,
        209
      ]
    },
    {
      "name": "PhaseChanged",
      "discriminator": [
        178,
        201,
        67,
        222,
        208,
        36,
        213,
        219
      ]
    },
    {
      "name": "PrivateWinnerComputed",
      "discriminator": [
        178,
        17,
        140,
        47,
        32,
        212,
        110,
        210
      ]
    }
  ],
  "errors": [
    {
      "code": 6000,
      "name": "AuctionNotInitialized",
      "msg": "Auction not initialized"
    },
    {
      "code": 6001,
      "name": "AuctionPhaseMismatch",
      "msg": "Wrong auction phase"
    },
    {
      "code": 6002,
      "name": "CommitWindowClosed",
      "msg": "Commit window closed"
    },
    {
      "code": 6003,
      "name": "RevealWindowClosed",
      "msg": "Reveal window closed"
    },
    {
      "code": 6004,
      "name": "CommitmentMismatch",
      "msg": "Commitment does not match reveal"
    },
    {
      "code": 6005,
      "name": "BidAlreadyCommitted",
      "msg": "Bid already committed"
    },
    {
      "code": 6006,
      "name": "BidAlreadyRevealed",
      "msg": "Bid already revealed"
    },
    {
      "code": 6007,
      "name": "RevealNotAllowed",
      "msg": "Reveal not allowed yet"
    },
    {
      "code": 6008,
      "name": "InsufficientFundsForDeposit",
      "msg": "Insufficient funds for deposit"
    },
    {
      "code": 6009,
      "name": "SettlementTooEarly",
      "msg": "Settlement too early"
    },
    {
      "code": 6010,
      "name": "AlreadySettled",
      "msg": "Auction already settled"
    },
    {
      "code": 6011,
      "name": "BidOutOfRange",
      "msg": "Bid amount out of range"
    },
    {
      "code": 6012,
      "name": "NoRevealedBids",
      "msg": "No revealed bids to settle"
    },
    {
      "code": 6013,
      "name": "SaltTooLong",
      "msg": "Salt too long"
    },
    {
      "code": 6014,
      "name": "InvalidMint",
      "msg": "Invalid token mint"
    },
    {
      "code": 6015,
      "name": "PrivateModeMismatch",
      "msg": "Private mode mismatch"
    },
    {
      "code": 6016,
      "name": "CiphertextTooLong",
      "msg": "Encrypted ciphertext too long"
    },
    {
      "code": 6017,
      "name": "WinnerNotComputed",
      "msg": "Winner not computed yet"
    },
    {
      "code": 6018,
      "name": "AggregateMismatch",
      "msg": "Ciphertext aggregate digest does not match on-chain bids"
    }
  ],
  "types": [
    {
      "name": "AuctionConfig",
      "type": {
        "kind": "struct",
        "fields": [
          {
            "name": "seller",
            "type": "pubkey"
          },
          {
            "name": "token_mint",
            "type": "pubkey"
          },
          {
            "name": "vault",
            "type": "pubkey"
          },
          {
            "name": "auction_id",
            "type": "u64"
          },
          {
            "name": "phase",
            "type": "u8"
          },
          {
            "name": "bidding_start",
            "type": "i64"
          },
          {
            "name": "commit_end",
            "type": "i64"
          },
          {
            "name": "reveal_end",
            "type": "i64"
          },
          {
            "name": "bump",
            "type": "u8"
          },
          {
            "name": "leader_bidder",
            "docs": [
              "Leader during reveal (first-price)."
            ],
            "type": "pubkey"
          },
          {
            "name": "leader_bid",
            "type": "u64"
          },
          {
            "name": "winner",
            "type": "pubkey"
          },
          {
            "name": "winning_price",
            "type": "u64"
          },
          {
            "name": "result_hash",
            "type": {
              "array": [
                "u8",
                32
              ]
            }
          },
          {
            "name": "commit_count",
            "type": "u32"
          },
          {
            "name": "reveal_count",
            "type": "u32"
          },
          {
            "name": "private_mode",
            "type": "bool"
          },
          {
            "name": "tee_winner_ready",
            "docs": [
              "TEE stage: computed before settle_private."
            ],
            "type": "bool"
          }
        ]
      }
    },
    {
      "name": "AuctionInitialized",
      "type": {
        "kind": "struct",
        "fields": [
          {
            "name": "auction_id",
            "type": "u64"
          },
          {
            "name": "seller",
            "type": "pubkey"
          },
          {
            "name": "token_mint",
            "type": "pubkey"
          },
          {
            "name": "private_mode",
            "type": "bool"
          }
        ]
      }
    },
    {
      "name": "AuctionRuntime",
      "docs": [
        "Delegated ER mirror for realtime UI (leader synced from AuctionConfig on base in reveal_bid)."
      ],
      "type": {
        "kind": "struct",
        "fields": [
          {
            "name": "auction_id",
            "type": "u64"
          },
          {
            "name": "leader_bid",
            "type": "u64"
          },
          {
            "name": "leader_bidder",
            "type": "pubkey"
          },
          {
            "name": "commit_count",
            "type": "u32"
          },
          {
            "name": "reveal_count",
            "type": "u32"
          },
          {
            "name": "bump",
            "type": "u8"
          }
        ]
      }
    },
    {
      "name": "AuctionSettled",
      "type": {
        "kind": "struct",
        "fields": [
          {
            "name": "auction_id",
            "type": "u64"
          },
          {
            "name": "winner",
            "type": "pubkey"
          },
          {
            "name": "winning_price",
            "type": "u64"
          },
          {
            "name": "result_hash",
            "type": {
              "array": [
                "u8",
                32
              ]
            }
          }
        ]
      }
    },
    {
      "name": "BidCiphertext",
      "docs": [
        "Private mode: encrypted bid payload (permissioned flow in TEE)."
      ],
      "type": {
        "kind": "struct",
        "fields": [
          {
            "name": "auction_id",
            "type": "u64"
          },
          {
            "name": "bidder",
            "type": "pubkey"
          },
          {
            "name": "ciphertext",
            "type": {
              "array": [
                "u8",
                256
              ]
            }
          },
          {
            "name": "ciphertext_len",
            "type": "u16"
          },
          {
            "name": "bump",
            "type": "u8"
          }
        ]
      }
    },
    {
      "name": "BidCommitment",
      "type": {
        "kind": "struct",
        "fields": [
          {
            "name": "auction_id",
            "type": "u64"
          },
          {
            "name": "bidder",
            "type": "pubkey"
          },
          {
            "name": "commitment",
            "type": {
              "array": [
                "u8",
                32
              ]
            }
          },
          {
            "name": "revealed",
            "type": "bool"
          },
          {
            "name": "bid_amount",
            "type": "u64"
          },
          {
            "name": "bump",
            "type": "u8"
          }
        ]
      }
    },
    {
      "name": "BidCommitted",
      "type": {
        "kind": "struct",
        "fields": [
          {
            "name": "auction_id",
            "type": "u64"
          },
          {
            "name": "bidder",
            "type": "pubkey"
          }
        ]
      }
    },
    {
      "name": "BidRevealed",
      "type": {
        "kind": "struct",
        "fields": [
          {
            "name": "auction_id",
            "type": "u64"
          },
          {
            "name": "bidder",
            "type": "pubkey"
          },
          {
            "name": "bid_amount",
            "type": "u64"
          }
        ]
      }
    },
    {
      "name": "PhaseChanged",
      "type": {
        "kind": "struct",
        "fields": [
          {
            "name": "auction_id",
            "type": "u64"
          },
          {
            "name": "new_phase",
            "type": "u8"
          }
        ]
      }
    },
    {
      "name": "PrivateWinnerComputed",
      "type": {
        "kind": "struct",
        "fields": [
          {
            "name": "auction_id",
            "type": "u64"
          },
          {
            "name": "winner",
            "type": "pubkey"
          },
          {
            "name": "winning_price",
            "type": "u64"
          },
          {
            "name": "result_hash",
            "type": {
              "array": [
                "u8",
                32
              ]
            }
          }
        ]
      }
    }
  ]
}